lzaas/__init__.py
lzaas_cli-1.0.1.dist-info/licenses/LICENSE
tests/__init__.py
tests/test_basic.py
lzaas_cli-1.0.1.dist-info/METADATA
lzaas_cli-1.0.1.dist-info/WHEEL
lzaas_cli-1.0.1.dist-info/entry_points.txt
lzaas_cli-1.0.1.dist-info/top_level.txt
lzaas_cli-1.0.1.dist-info/RECORD
